mynotes/__init__.py
mynotes/cli.py
mynotes_cli-0.3.7.dist-info/licenses/LICENSE
mynotes_cli-0.3.7.dist-info/METADATA
mynotes_cli-0.3.7.dist-info/WHEEL
mynotes_cli-0.3.7.dist-info/entry_points.txt
mynotes_cli-0.3.7.dist-info/top_level.txt
mynotes_cli-0.3.7.dist-info/RECORD
