Metadata-Version: 2.4
Name: mynotes-cli
Version: 0.3.7
Summary: CLI notes manager with tags, colored output, exports and shell autocompletion
Author-email: Antonín Šiška <your.email@example.com>
License-Expression: MIT
Project-URL: Homepage, https://github.com/antoninsiska/mynotes-cli
Project-URL: Repository, https://github.com/antoninsiska/mynotes-cli
Project-URL: Issues, https://github.com/antoninsiska/mynote-cli/issues
Keywords: notes,cli,terminal,tags,productivity,python
Classifier: Development Status :: 4 - Beta
Classifier: Environment :: Console
Classifier: Intended Audience :: End Users/Desktop
Classifier: Operating System :: OS Independent
Classifier: Programming Language :: Python :: 3
Classifier: Topic :: Utilities
Requires-Python: >=3.8
License-File: LICENSE
Requires-Dist: rich>=13
Requires-Dist: argcomplete>=3
Dynamic: license-file
